{
  "id": "event-250809",
  "name": "Leo's Birthday Bash",
  "date": "2025-08-09T18:00:00",
  "end_date": "2025-08-10T00:00:00",
  "location": "Queen Bee, 4198 Convoy St, San Diego, CA 92111",
  "maps_link": "https://maps.app.goo.gl/uUM7UZVY814Unu8c9",
  "type": ["bachata", "timba", "rueda"],
  "music": "DJ",
  "price": "Free",
  "description": "Let's celebrate Leo's birthday with a special bachata and timba night! Join us for a fun evening of dancing, drinks, and community.",
  "contact": "@cubansocial.sd",
  "featured": true,
  "created_at": "2025-07-27T09:00:00Z"
}
